raisin/__init__.py
raisin/__main__.py
raisin/doc.py
raisin/raisin.py
raisin/application/__init__.py
raisin/application/configuration.py
raisin/application/install.py
raisin/application/location.py
raisin/application/port.py
raisin/application/uninstall.py
raisin/application/verbosity.py
raisin/communication/__init__.py
raisin/communication/abstraction.py
raisin/communication/client.py
raisin/communication/handler.py
raisin/communication/request.py
raisin/communication/server.py
raisin/communication/test_communication.py
raisin/encapsulation/__init__.py
raisin/encapsulation/formatting.py
raisin/encapsulation/manager.py
raisin/encapsulation/packaging.py
raisin/serialization/__init__.py
raisin/serialization/constants.py
raisin/serialization/core.py
raisin/serialization/iter_tools.py
raisin/serialization/test_iter_tools.py
raisin/serialization/test_serialization.py
raisin/serialization/atoms/__init__.py
raisin/serialization/atoms/dumps.py
raisin/serialization/atoms/iterator.py
raisin/serialization/atoms/raisin_class.py
raisin/serialization/atoms/small.py
raisin/serialization/atoms/source_code.py
raisin-3.0.5.dist-info/LICENSE
raisin-3.0.5.dist-info/METADATA
raisin-3.0.5.dist-info/WHEEL
raisin-3.0.5.dist-info/entry_points.txt
raisin-3.0.5.dist-info/top_level.txt
raisin-3.0.5.dist-info/RECORD
