Metadata-Version: 2.1
Name: raisin
Version: 3.0.5
Summary: Simple parallel, distributed and cluster computing
Home-page: https://framagit.org/robinechuca/raisin/-/blob/master/README.rst
Author: Robin RICHARD (robinechuca)
Author-email: raisin@ecomail.fr
License: UNKNOWN
Project-URL: Source Repository, https://framagit.org/robinechuca/raisin
Project-URL: Documentation, http://raisin-docs.ddns.net
Keywords: parallel,parallelisation,distributed,cluster work,cluster computing,serialization,serializeclient,server
Platform: UNKNOWN
Classifier: Development Status :: 4 - Beta
Classifier: Intended Audience :: Developers
Classifier: Intended Audience :: Science/Research
Classifier: License :: OSI Approved :: GNU Affero General Public License v3 or later (AGPLv3+)
Classifier: Natural Language :: English
Classifier: Operating System :: POSIX :: Linux
Classifier: Programming Language :: Python :: 3.6
Classifier: Programming Language :: Python :: 3.7
Classifier: Programming Language :: Python :: 3.8
Classifier: Programming Language :: Python :: 3.9
Classifier: Programming Language :: Python :: 3.10
Classifier: Topic :: System :: Distributed Computing
Classifier: Topic :: System :: Clustering
Classifier: Topic :: Internet
Classifier: Topic :: Scientific/Engineering
Classifier: Topic :: Software Development
Classifier: Topic :: System :: Power (UPS)
License-File: LICENSE
Requires-Dist: dill
Requires-Dist: context-verbose
Provides-Extra: documentation
Requires-Dist: pdoc3 ; extra == 'documentation'
Requires-Dist: pyreverse ; extra == 'documentation'
Provides-Extra: tests
Requires-Dist: pytest ; extra == 'tests'
